MANIFEST.in
README.md
setup.py
aiei/__init__.py
aiei/info.py
aiei.egg-info/PKG-INFO
aiei.egg-info/SOURCES.txt
aiei.egg-info/dependency_links.txt
aiei.egg-info/not-zip-safe
aiei.egg-info/requires.txt
aiei.egg-info/top_level.txt
aiei/core/__init__.py
aiei/core/aiei.py
aiei/core/base_config.py
aiei/ctrib/__init__.py
aiei/ctrib/dsn.py
aiei/ctrib/soft_argmax.py
aiei/data/__init__.py
aiei/data/mixup.py
aiei/data/sampler.py
aiei/data/utils.py
aiei/data/set/__init__.py
aiei/data/set/coco.py
aiei/data/transform/__init__.py
aiei/data/transform/base_cls.py
aiei/data/transform/base_fn.py
aiei/data/transform/center_pad.py
aiei/data/transform/normalize.py
aiei/data/transform/random_affine.py
aiei/data/transform/random_brightness.py
aiei/data/transform/random_contrast.py
aiei/data/transform/random_crop.py
aiei/data/transform/random_erase.py
aiei/data/transform/random_flip.py
aiei/data/transform/random_lighting.py
aiei/data/transform/random_saturation.py
aiei/data/transform/resize_edge.py
aiei/data/transform/to_tensor.py
aiei/misc/__init__.py
aiei/misc/alg.py
aiei/misc/dist.py
aiei/misc/dotsi.py
aiei/misc/logger.py
aiei/misc/mix.py
aiei/misc/summary.py
aiei/misc/video.py
aiei/misc/vis.py
aiei/model/__init__.py
aiei/model/function.py
aiei/model/init.py
aiei/model/zlayers.py
aiei/model/backbones/__init__.py
aiei/model/backbones/darknet.py
aiei/model/backbones/densenet.py
aiei/model/backbones/dla.py
aiei/model/backbones/efficientnet.py
aiei/model/backbones/hgnet.py
aiei/model/backbones/highernet.py
aiei/model/backbones/hrnet.py
aiei/model/backbones/resnet.py
aiei/model/backbones/shufflenetv2.py
aiei/model/backbones/tnet.py
aiei/model/layers/__init__.py
aiei/model/layers/cbam.py
aiei/model/layers/coord_conv.py
aiei/model/layers/gau_fpa.py
aiei/model/layers/norm.py
aiei/model/layers/self_attention.py
aiei/ops/__init__.py
aiei/ops/FAIR/__init__.py
aiei/ops/FAIR/deform_conv.py
aiei/ops/FAIR/deform_conv_with_off.py
aiei/ops/FAIR/nms.py
aiei/ops/FAIR/roi_align.py
aiei/ops/FAIR/setup.py
aiei/ops/FAIR/ROIAlign/ROIAlign.h
aiei/ops/FAIR/deformable/deform_conv.h
aiei/ops/dcnv2/__init__.py
aiei/ops/dcnv2/setup.py
aiei/ops/dcnv2/functions/__init__.py
