Metadata-Version: 2.1
Name: aiei
Version: 1.0.7
Summary: A tiny framework for AI.
Home-page: UNKNOWN
Author: Lei Zhao
Author-email: zlchn@qq.com
License: Apache
Project-URL: github, https://github.com/
Keywords: deep learning,pytorch,AI,EI
Platform: UNKNOWN
Classifier: License :: OSI Approved :: Apache Software License
Classifier: Programming Language :: Python
Classifier: Programming Language :: Python :: 3
Classifier: Programming Language :: Python :: 3.6
Classifier: Programming Language :: Python :: Implementation :: CPython
Classifier: Programming Language :: Python :: Implementation :: PyPy
Requires-Python: >=3.6.0
Provides-Extra: dev
